libdata/__init__.py
libdata/models/__init__.py
libdata/models/tables.py
libdata/settings.py
data_layer_lib-1.0.2.dist-info/METADATA
data_layer_lib-1.0.2.dist-info/WHEEL
data_layer_lib-1.0.2.dist-info/RECORD
