Metadata-Version: 2.1
Name: data-layer-lib
Version: 1.0.2
Summary: Database layer library
Author: Arif Nawaz
Requires-Python: >=3.9,<4.0
Classifier: Programming Language :: Python :: 3
Classifier: Programming Language :: Python :: 3.9
Classifier: Programming Language :: Python :: 3.10
Classifier: Programming Language :: Python :: 3.11
Requires-Dist: alembic (>=1.10.2,<2.0.0)
Requires-Dist: black (>=23.3.0,<24.0.0)
Requires-Dist: psycopg2-binary (>=2.9.3,<3.0.0)
Requires-Dist: pydantic (>=1.10.7,<2.0.0)
Requires-Dist: pylint (>=2.17.1,<3.0.0)
Requires-Dist: pytest (>=7.2.2,<8.0.0)
Requires-Dist: sqlalchemy (==2.0.7)
